{
  "updated_at": "2026-07-07T09:43:56.415413+07:00",
  "banks": {
    "vietcombank": {
      "name": "Vietcombank",
      "rates": [
        {
          "currency": "USD",
          "buy_cash": 26072.0,
          "buy_transfer": 26102.0,
          "sell": 26462.0
        },
        {
          "currency": "AUD",
          "buy_cash": 17815.85,
          "buy_transfer": 17995.81,
          "sell": 18572.13
        },
        {
          "currency": "EUR",
          "buy_cash": 29314.66,
          "buy_transfer": 29610.77,
          "sell": 30860.13
        },
        {
          "currency": "JPY",
          "buy_cash": 156.55,
          "buy_transfer": 158.13,
          "sell": 167.35
        },
        {
          "currency": "GBP",
          "buy_cash": 34309.35,
          "buy_transfer": 34655.91,
          "sell": 35765.77
        }
      ],
      "error": false,
      "error_msg": null
    },
    "bidv": {
      "name": "BIDV",
      "rates": [
        {
          "currency": "USD",
          "buy_cash": 26102.0,
          "buy_transfer": 26102.0,
          "sell": 26462.0
        },
        {
          "currency": "AUD",
          "buy_cash": 17947.0,
          "buy_transfer": 18012.0,
          "sell": 18675.0
        },
        {
          "currency": "EUR",
          "buy_cash": 29584.0,
          "buy_transfer": 29608.0,
          "sell": 30994.0
        },
        {
          "currency": "JPY",
          "buy_cash": 157.84,
          "buy_transfer": 158.12,
          "sell": 167.55
        },
        {
          "currency": "GBP",
          "buy_cash": 34594.0,
          "buy_transfer": 34688.0,
          "sell": 35857.0
        }
      ],
      "error": false,
      "error_msg": null
    },
    "vietinbank": {
      "name": "VietinBank",
      "rates": [],
      "error": true,
      "error_msg": "Fetch failed"
    },
    "techcombank": {
      "name": "Techcombank",
      "rates": [
        {
          "currency": "USD",
          "buy_cash": 26104.0,
          "buy_transfer": 26118.0,
          "sell": 26462.0
        },
        {
          "currency": "AUD",
          "buy_cash": 17756.0,
          "buy_transfer": 18029.0,
          "sell": 18610.0
        },
        {
          "currency": "EUR",
          "buy_cash": 29463.0,
          "buy_transfer": 29684.0,
          "sell": 30762.0
        },
        {
          "currency": "JPY",
          "buy_cash": 155.77,
          "buy_transfer": 159.93,
          "sell": 166.07
        },
        {
          "currency": "GBP",
          "buy_cash": 34424.0,
          "buy_transfer": 34815.0,
          "sell": 35760.0
        }
      ],
      "error": false,
      "error_msg": null
    },
    "agribank": {
      "name": "Agribank",
      "rates": [
        {
          "currency": "USD",
          "buy_cash": 26082.0,
          "buy_transfer": 26102.0,
          "sell": 26462.0
        },
        {
          "currency": "AUD",
          "buy_cash": 17924.0,
          "buy_transfer": 17996.0,
          "sell": 18591.0
        },
        {
          "currency": "EUR",
          "buy_cash": 29517.0,
          "buy_transfer": 29636.0,
          "sell": 30829.0
        },
        {
          "currency": "JPY",
          "buy_cash": 158.1,
          "buy_transfer": 158.73,
          "sell": 166.65
        },
        {
          "currency": "GBP",
          "buy_cash": 34581.0,
          "buy_transfer": 34720.0,
          "sell": 35750.0
        }
      ],
      "error": false,
      "error_msg": null
    },
    "acb": {
      "name": "ACB",
      "rates": [
        {
          "currency": "USD",
          "buy_cash": 26080.0,
          "buy_transfer": 26110.0,
          "sell": 26462.0
        },
        {
          "currency": "AUD",
          "buy_cash": 17919.0,
          "buy_transfer": 18036.0,
          "sell": 18608.0
        },
        {
          "currency": "EUR",
          "buy_cash": 29510.0,
          "buy_transfer": 29629.0,
          "sell": 30744.0
        },
        {
          "currency": "JPY",
          "buy_cash": 159.05,
          "buy_transfer": 159.85,
          "sell": 166.51
        },
        {
          "currency": "GBP",
          "buy_cash": null,
          "buy_transfer": 34755.0,
          "sell": 35732.0
        }
      ],
      "error": false,
      "error_msg": null
    },
    "mbbank": {
      "name": "MBBank",
      "rates": [],
      "error": true,
      "error_msg": "HTTP 403"
    },
    "sacombank": {
      "name": "Sacombank",
      "rates": [
        {
          "currency": "USD",
          "buy_cash": 26100.0,
          "buy_transfer": 26100.0,
          "sell": 26462.0
        },
        {
          "currency": "AUD",
          "buy_cash": 17932.0,
          "buy_transfer": 18032.0,
          "sell": 18954.0
        },
        {
          "currency": "EUR",
          "buy_cash": 29631.0,
          "buy_transfer": 29661.0,
          "sell": 31386.0
        },
        {
          "currency": "JPY",
          "buy_cash": 158.67,
          "buy_transfer": 159.17,
          "sell": 169.68
        },
        {
          "currency": "GBP",
          "buy_cash": 34706.0,
          "buy_transfer": 34756.0,
          "sell": 36514.0
        }
      ],
      "error": false,
      "error_msg": null
    },
    "vpbank": {
      "name": "VPBank",
      "rates": [],
      "error": true,
      "error_msg": "Rate table not found in HTML"
    },
    "tpbank": {
      "name": "TPBank",
      "rates": [],
      "error": false,
      "error_msg": null
    }
  }
}